{"cameraMode":{"drawMode":0,"name":"Shaded","section":"Shading Mode"},"sceneLighting":false,"audioPlay":false,"sceneViewState":{"m_AlwaysRefresh":false,"showFog":true,"showSkybox":false,"showFlares":true,"showImageEffects":true,"showParticleSystems":true,"showVisualEffectGraphs":true,"m_FxEnabled":true},"in2DMode":false,"pivot":{"x":118.93818664550781,"y":0.12192440032958985,"z":20.23959732055664},"rotation":{"x":0.15132494270801545,"y":0.24003855884075166,"z":-0.04415849223732948,"w":0.9585313200950623},"size":5.934922695159912,"orthographic":false}