{"cameraMode":{"drawMode":0,"name":"Shaded","section":"Shading Mode"},"sceneLighting":true,"audioPlay":false,"sceneViewState":{"m_AlwaysRefresh":false,"showFog":true,"showSkybox":true,"showFlares":true,"showImageEffects":true,"showParticleSystems":true,"showVisualEffectGraphs":true,"m_FxEnabled":true},"in2DMode":false,"pivot":{"x":49.556331634521487,"y":16.80350112915039,"z":43.14752197265625},"rotation":{"x":-0.5391435623168945,"y":0.11019471287727356,"z":-0.07084644585847855,"w":-0.8322016596794128},"size":67.83174133300781,"orthographic":false}